README.md
setup.py
src/vdk/plugin/logging_ltsv/logging_ltsv.py
src/vdk_logging_ltsv.egg-info/PKG-INFO
src/vdk_logging_ltsv.egg-info/SOURCES.txt
src/vdk_logging_ltsv.egg-info/dependency_links.txt
src/vdk_logging_ltsv.egg-info/entry_points.txt
src/vdk_logging_ltsv.egg-info/requires.txt
src/vdk_logging_ltsv.egg-info/top_level.txt