Metadata-Version: 2.1
Name: vdk-logging-ltsv
Version: 0.1.414800992
Summary: Versatile Data Kit SDK plugin that changes logging output to LTSV format.
Home-page: https://github.com/vmware/versatile-data-kit
License: UNKNOWN
Platform: UNKNOWN
Classifier: Development Status :: 4 - Beta
Classifier: License :: OSI Approved :: Apache Software License
Classifier: Programming Language :: Python :: 3.7
Classifier: Programming Language :: Python :: 3.8
Classifier: Programming Language :: Python :: 3.9
Classifier: Programming Language :: Python :: 3.10
